Workbook

Sheet Sheet1
A1: Order_ID | B1: Order_Date | C1: Customer_ID | D1: Product | E1: Category | F1: Quantity | G1: Unit_Price | H1: Discount_% | I1: Sales | J1: Profit | K1: Country | L1: Payment_Method
A2: ORD001 | B2: 45327 | C2: CUST18 | D2: Mouse | E2: Accessories | F2: -1 | G2: 2139 | H2: 10 | I2: -1925.1 | J2: 3.93 | K2: India | L2: UPI
A3: ORD002 | B3: 45342 | C3: CUST18 | D3: Phone | E3: Electronics | F3: 1 | G3: 33618 | H3: 20 | I3: 26894.4 | J3: -2403.97 | K3: UK | L3: UPI
A4: ORD003 | B4: 45378 | C4: CUST13 | D4: Phone | E4: Electronics | F4: 4 | G4: 22798 | H4: 10 | I4: 82072.8 | J4: -3103.02 | K4: UK | L4: UPI
A5: ORD004 | B5: 45388 | C5: CUST10 | D5: Mouse | E5: Accessories | F5: 5 | G5: 35642 | H5: 0 | I5: 178210 | J5: 51546.58 | K5: UK | L5: Credit Card
A6: ORD005 | B6: 45312 | C6: CUST4 | D6: Mouse | E6: Accessories | F6: -1 | G6: 3503 | H6: 5 | I6: -3327.85 | J6: -696.28 | K6: UK | L6: Credit Card
A7: ORD006 | B7: 45466 | C7: CUST20 | D7: Headphones | E7: Accessories | F7: 3 | G7: 14230 | H7: 10 | I7: 38421 | J7: 6943.76 | K7: USA | L7: Credit Card
A8: ORD007 | B8: 45375 | C8: CUST2 | D8: Keyboard | E8: Accessories | G8: 18191 | H8: 20 | I8: 58211.2 | J8: -707.49 | K8: UK | L8: Net Banking
A9: ORD008 | B9: 45372 | C9: CUST16 | D9: Headphones | E9: Accessories | F9: -1 | G9: 14326 | H9: 20 | I9: -11460.8 | J9: -2871.47 | K9: Canada | L9: Credit Card
A10: ORD009 | B10: 45441 | C10: CUST19 | D10: Headphones | E10: Accessories | F10: 0 | G10: 16662 | H10: 20 | I10: 0 | J10: 0 | K10: USA | L10: Net Banking
A11: ORD010 | B11: 45466 | C11: CUST3 | D11: Laptop | E11: Electronics | F11: -2 | G11: 7685 | H11: 5 | I11: -14601.5 | J11: -2204.51 | K11: Canada | L11: Debit Card
A12: ORD011 | B12: 45429 | C12: CUST11 | D12: Monitor | E12: Electronics | F12: -2 | G12: 45083 | H12: 0 | I12: -90166 | J12: -15570.24 | K12: Canada | L12: UPI
A13: ORD012 | B13: 45319 | C13: CUST10 | D13: Mouse | E13: Accessories | F13: 2 | G13: 33306 | H13: 5 | I13: 63281.4 | J13: 6522.58 | K13: USA | L13: Credit Card
A14: ORD013 | B14: 45445 | C14: CUST1 | D14: Headphones | E14: Accessories | F14: 0 | G14: 35848 | H14: 20 | I14: 0 | J14: 0 | K14: UK | L14: Credit Card
A15: ORD014 | B15: 45416 | C15: CUST18 | D15: Laptop | E15: Electronics | F15: 1 | G15: 37682 | H15: 0 | I15: 37682 | J15: -2477.16 | K15: Canada | L15: Credit Card
A16: ORD015 | B16: 45468 | C16: CUST10 | D16: Headphones | E16: Accessories | F16: 4 | G16: 14380 | H16: 20 | I16: 46016 | J16: 9300.11 | K16: UK | L16: Net Banking
A17: ORD016 | B17: wrong_date | C17: CUST18 | D17: Monitor | E17: Electronics | F17: 5 | G17: 8430 | H17: 5 | I17: 40042.5 | J17: -405.27 | K17: India | L17: UPI
A18: ORD017 | B18: 45352 | C18: CUST16 | D18: Phone | E18: Electronics | F18: -1 | G18: 2558 | H18: 10 | I18: -2302.2 | J18: 164.97 | K18: Canada | L18: Credit Card
A19: ORD018 | B19: 45402 | C19: CUST14 | D19: Keyboard | E19: Accessories | F19: 4 | G19: 12978 | H19: 0 | I19: 51912 | J19: -3178.45 | K19: India | L19: UPI
A20: ORD019 | B20: 45429 | C20: CUST14 | D20: Keyboard | E20: Accessories | F20: 3 | G20: 7661 | H20: 5 | I20: 21833.85 | J20: -510.13 | K20: India | L20: Net Banking
A21: ORD020 | B21: 45315 | C21: CUST8 | D21: Monitor | E21: Electronics | F21: -1 | G21: 3815 | H21: 20 | I21: -3052 | J21: -715.42 | K21: USA | L21: Net Banking
A22: ORD021 | B22: 45359 | C22: CUST15 | D22: Laptop | E22: Electronics | F22: 0 | G22: 25336 | H22: 0 | I22: 0 | J22: 0 | K22: Canada | L22: Credit Card
A23: ORD022 | B23: 45430 | C23: CUST11 | D23: Phone | E23: Electronics | F23: 2 | G23: 14767 | H23: 0 | I23: 29534 | J23: 3888.8 | K23: USA | L23: UPI
A24: ORD023 | B24: 45464 | C24: CUST13 | D24: Monitor | E24: Electronics | F24: -1 | G24: 12678 | H24: 0 | I24: -12678 | J24: -1749.74 | K24: USA | L24: UPI
A25: ORD024 | B25: 45372 | C25: CUST7 | D25: Monitor | E25: Electronics | F25: -1 | G25: 27974 | H25: 20 | I25: -22379.2 | J25: -2821.81 | K25: UK | L25: Net Banking
A26: ORD025 | B26: wrong_date | C26: CUST20 | D26: Phone | E26: Electronics | F26: 2 | G26: 30464 | H26: 10 | I26: 54835.2 | J26: 14893.64 | K26: India | L26: Credit Card
A27: ORD026 | B27: 45354 | C27: CUST6 | D27: Monitor | E27: Electronics | F27: 2 | G27: 9180 | H27: 10 | I27: 16524 | J27: 4169.76 | K27: UK | L27: UPI
A28: ORD027 | B28: 45326 | C28: CUST4 | D28: Mouse | E28: Accessories | F28: 2 | G28: 43975 | H28: 0 | I28: 87950 | J28: 24236.56 | K28: UK | L28: Credit Card
A29: ORD028 | B29: 45356 | C29: CUST2 | D29: Mouse | E29: Accessories | F29: 3 | G29: 13842 | H29: 10 | I29: 37373.4 | J29: 3818.2 | K29: UK | L29: UPI
A30: ORD029 | B30: 45405 | C30: CUST14 | D30: Laptop | E30: Electronics | F30: 3 | G30: 9073 | H30: 10 | I30: 24497.1 | J30: -866.39 | K30: USA | L30: UPI
A31: ORD030 | B31: 45385 | C31: CUST2 | D31: Headphones | E31: Accessories | F31: 0 | G31: 28666 | H31: 5 | I31: 0 | J31: 0 | K31: USA | L31: UPI
A32: ORD031 | B32: 45352 | C32: CUST6 | D32: Headphones | E32: Accessories | G32: 41175 | H32: 5 | I32: 156465 | J32: 42293.35 | K32: UK | L32: Net Banking
A33: ORD032 | B33: 45319 | C33: CUST2 | D33: Mouse | E33: Accessories | F33: 1 | G33: 17985 | H33: 5 | I33: 17085.75 | J33: 3672.58 | K33: Canada | L33: Debit Card
A34: ORD033 | B34: 45394 | C34: CUST3 | D34: Headphones | E34: Accessories | F34: 1 | G34: 15109 | H34: 0 | I34: 15109 | J34: 2478.08 | K34: Canada | L34: Debit Card
A35: ORD034 | B35: wrong_date | C35: CUST20 | D35: Laptop | E35: Electronics | F35: -1 | G35: 17618 | H35: 5 | I35: -16737.1 | J35: -2213.25 | K35: UK | L35: Net Banking
A36: ORD035 | B36: 45303 | C36: CUST1 | D36: Monitor | E36: Electronics | F36: -1 | G36: 25744 | H36: 20 | I36: -20595.2 | J36: 493.64 | K36: USA | L36: Debit Card
A37: ORD036 | B37: 45461 | C37: CUST10 | D37: Keyboard | E37: Accessories | F37: -1 | G37: 44031 | H37: 10 | I37: -39627.9 | J37: -5914.95 | K37: UK | L37: Net Banking
A38: ORD037 | B38: 45462 | C38: CUST6 | D38: Mouse | E38: Accessories | F38: 2 | G38: 36833 | H38: 5 | I38: 69982.7 | J38: -1628.07 | K38: India | L38: Debit Card
A39: ORD038 | B39: 45374 | C39: CUST15 | D39: Headphones | E39: Accessories | F39: 1 | G39: 28673 | H39: 20 | I39: 22938.4 | J39: 3272.5 | K39: USA | L39: UPI
A40: ORD039 | B40: 45349 | C40: CUST5 | D40: Headphones | E40: Eletronics | F40: 3 | G40: 6620 | H40: 5 | I40: 18867 | J40: 3190.75 | K40: Canada | L40: UPI
A41: ORD040 | B41: 45470 | C41: CUST13 | D41: Keyboard | E41: Accessories | F41: 4 | G41: 41772 | H41: 20 | I41: 133670.4 | J41: -2970.95 | K41: India | L41: UPI
A42: ORD041 | B42: 45434 | C42: CUST4 | D42: Keyboard | E42: Accessories | F42: 1 | G42: 12026 | H42: 20 | I42: 9620.8 | J42: 825.66 | K42: UK | L42: Net Banking
A43: ORD042 | B43: 45413 | C43: CUST8 | D43: Monitor | E43: Electronics | F43: 4 | G43: 36405 | H43: 15 | I43: 123777 | J43: 32043.79 | K43: Canada | L43: Credit Card
A44: ORD043 | B44: 45377 | C44: CUST18 | D44: Headphones | E44: Accessories | F44: 5 | G44: 5577 | H44: 10 | I44: 25096.5 | J44: -155.66 | K44: Canada | L44: Credit Card
A45: ORD044 | B45: 45430 | C45: CUST2 | D45: Mouse | E45: Accessories | F45: 1 | G45: 4709 | H45: 15 | I45: 4002.65 | J45: 252.33 | K45: India | L45: Net Banking
A46: ORD045 | B46: 45399 | C46: CUST18 | D46: Keyboard | E46: Accessories | F46: -2 | G46: 23552 | H46: 10 | I46: -42393.6 | J46: -8537.65 | K46: Canada | L46: Credit Card
A47: ORD046 | B47: 45463 | C47: CUST13 | D47: Headphones | E47: Accessories | F47: 4 | G47: 32327 | H47: 0 | I47: 129308 | J47: 7182.14 | K47: USA | L47: UPI
... A56: ORD055 | B56: 45444 | C56: CUST9 | D56: Keyboard | E56: Accessories | F56: 1 | G56: 23753 | H56: 10 | I56: 21377.7 | J56: 772.49 | K56: USA | L56: UPI
A57: ORD056 | B57: 45468 | C57: CUST16 | D57: Phone | E57: Electronics | G57: 32519 | H57: 20 | I57: 104060.8 | J57: 21152.01 | K57: UK | L57: Credit Card
A58: ORD057 | B58: 45433 | C58: CUST14 | D58: Keyboard | E58: Accessories | F58: 1 | G58: 20567 | H58: 20 | I58: 16453.6 | J58: 783.33 | K58: UK | L58: Net Banking
A59: ORD058 | B59: 45341 | C59: CUST18 | D59: Headphones | E59: Accessories | F59: 2 | G59: 16975 | H59: 5 | I59: 32252.5 | J59: -1668.67 | K59: USA | L59: Credit Card
A60: ORD059 | B60: 45426 | C60: CUST4 | D60: Mouse | E60: Accessories | F60: 5 | G60: 18620 | H60: 20 | I60: 74480 | J60: 21647.08 | K60: UK | L60: Credit Card
A61: ORD060 | B61: 45303 | C61: CUST18 | D61: Headphones | E61: Accessories | F61: -2 | G61: 46900 | H61: 20 | I61: -75040 | J61: 3704.49 | K61: Canada | L61: UPI
A62: ORD061 | B62: 45339 | C62: CUST9 | D62: Laptop | E62: Electronics | F62: 2 | G62: 31262 | H62: 15 | I62: 53145.4 | J62: 4049.02 | K62: India | L62: Net Banking
A63: ORD062 | B63: 45436 | C63: CUST3 | D63: Keyboard | E63: Accessories | F63: -1 | G63: 38315 | H63: 0 | I63: -38315 | J63: 1506.13 | K63: Canada | L63: Credit Card
A64: ORD063 | B64: 45442 | C64: CUST10 | D64: Monitor | E64: Electronics | F64: 4 | G64: 30024 | H64: 15 | I64: 102081.6 | J64: 1933.55 | K64: India | L64: Credit Card
A65: ORD064 | B65: 45336 | C65: CUST6 | D65: Mouse | E65: Eletronics | F65: 1 | G65: 17843 | H65: 0 | I65: 17843 | J65: -663.35 | K65: Canada | L65: Debit Card
A66: ORD065 | B66: 45408 | C66: CUST8 | D66: Laptop | E66: Electronics | F66: 1 | G66: 19381 | H66: 10 | I66: 17442.9 | J66: 3160.57 | K66: USA | L66: Net Banking
A67: ORD066 | B67: 45328 | C67: CUST6 | D67: Laptop | E67: Electronics | F67: 1 | G67: 42943 | H67: 5 | I67: 40795.85 | J67: 10744.18 | K67: UK | L67: Net Banking
A68: ORD067 | B68: 45361 | C68: CUST16 | D68: Laptop | E68: Electronics | F68: 5 | G68: 45633 | H68: 10 | I68: 205348.5 | J68: 36940.86 | K68: Canada | L68: Debit Card
A69: ORD068 | B69: 45464 | C69: CUST19 | D69: Monitor | E69: Electronics | G69: 2195 | H69: 0 | I69: 4390 | J69: -37.01 | K69: UK | L69: UPI
A70: ORD069 | B70: 45338 | C70: CUST14 | D70: Phone | E70: Electronics | F70: 5 | G70: 34510 | H70: 15 | I70: 146667.5 | J70: 39076.49 | K70: India | L70: Net Banking
A71: ORD070 | B71: 45333 | C71: CUST16 | D71: Headphones | E71: Accessories | F71: 4 | G71: 22343 | H71: 10 | I71: 80434.8 | J71: 13517.34 | K71: India | L71: Net Banking
A72: ORD071 | B72: 45395 | C72: CUST1 | D72: Laptop | E72: Electronics | F72: 3 | G72: 17041 | H72: 10 | I72: 46010.7 | J72: -2467.62 | K72: Canada | L72: UPI
A73: ORD072 | B73: 45305 | C73: CUST18 | D73: Phone | E73: Electronics | F73: 3 | G73: 41304 | H73: 15 | I73: 105325.2 | J73: 15816 | K73: Canada | L73: UPI
A74: ORD073 | B74: 45295 | C74: CUST3 | D74: Laptop | E74: Electronics | F74: 1 | G74: 47016 | H74: 5 | I74: 44665.2 | J74: 1085.37 | K74: India | L74: Net Banking
A75: ORD074 | B75: 45361 | C75: CUST16 | D75: Laptop | E75: Electronics | F75: 0 | G75: 33161 | H75: 10 | I75: 0 | J75: 0 | K75: USA | L75: Net Banking
A76: ORD075 | B76: 45398 | C76: CUST17 | D76: Phone | E76: Electronics | G76: 5075 | H76: 10 | I76: 0 | J76: 0 | K76: UK | L76: Net Banking
A77: ORD076 | B77: 45433 | C77: CUST13 | D77: Phone | E77: Electronics | F77: 5 | G77: 35796 | H77: 15 | I77: 152133 | J77: 5788.6 | K77: USA | L77: Credit Card
A78: ORD077 | B78: 45413 | C78: CUST13 | D78: Monitor | E78: Electronics | F78: 4 | G78: 15806 | H78: 15 | I78: 53740.4 | J78: -4435.79 | K78: USA | L78: Net Banking
A79: ORD078 | B79: 45317 | C79: CUST15 | D79: Laptop | E79: Electronics | F79: 0 | G79: 33418 | H79: 20 | I79: 0 | J79: 0 | K79: India | L79: Credit Card
A80: ORD079 | B80: 45359 | C80: CUST13 | D80: Keyboard | E80: Accessories | F80: 0 | G80: 5403 | H80: 15 | I80: 0 | J80: 0 | K80: Canada | L80: Debit Card
A81: ORD080 | B81: 45352 | C81: CUST10 | D81: Mouse | E81: Accessories | F81: 5 | G81: 35956 | H81: 0 | I81: 179780 | J81: 26424.74 | K81: Canada | L81: UPI
A82: ORD081 | B82: wrong_date | C82: CUST2 | D82: Mouse | E82: Accessories | F82: -1 | G82: 29576 | H82: 5 | I82: -28097.2 | J82: -4990.08 | K82: USA | L82: Credit Card
A83: ORD082 | B83: 45312 | C83: CUST13 | D83: Monitor | E83: Electronics | F83: 4 | G83: 37588 | H83: 5 | I83: 142834.4 | J83: -4571.63 | K83: USA | L83: Credit Card
A84: ORD083 | B84: 45411 | C84: CUST18 | D84: Keyboard | E84: Accessories | F84: 2 | G84: 30618 | H84: 10 | I84: 55112.4 | J84: 9189.24 | K84: UK | L84: Debit Card
A85: ORD084 | B85: 45369 | C85: CUST13 | D85: Mouse | E85: Accessories | F85: 4 | G85: 45740 | H85: 10 | I85: 164664 | J85: 13623.36 | K85: Canada | L85: Debit Card
A86: ORD085 | B86: 45460 | C86: CUST1 | D86: Monitor | E86: Electronics | F86: 2 | G86: 46327 | H86: 10 | I86: 83388.6 | J86: -7607.06 | K86: India | L86: Net Banking
A87: ORD086 | B87: 45340 | C87: CUST5 | D87: Headphones | E87: Accessories | F87: 1 | G87: 40284 | H87: 10 | I87: 36255.6 | J87: -449.5 | K87: India | L87: Debit Card
A88: ORD087 | B88: 45315 | C88: CUST11 | D88: Keyboard | E88: Accessories | F88: -2 | G88: 38482 | H88: 10 | I88: -69267.6 | J88: -13364.76 | K88: USA | L88: Debit Card
A89: ORD088 | B89: 45415 | C89: CUST10 | D89: Monitor | E89: Electronics | F89: 2 | G89: 11283 | H89: 10 | I89: 20309.4 | J89: 5394.57 | K89: India | L89: Net Banking
A90: ORD089 | B90: 45464 | C90: CUST18 | D90: Laptop | E90: Electronics | F90: 0 | G90: 49924 | H90: 5 | I90: 0 | J90: 0 | K90: India | L90: Debit Card
A91: ORD090 | B91: 45464 | C91: CUST13 | D91: Monitor | E91: Electronics | F91: -1 | G91: 30304 | H91: 10 | I91: -27273.6 | J91: -4612.82 | K91: India | L91: Credit Card
A92: ORD091 | B92: 45448 | C92: CUST3 | D92: Keyboard | E92: Accessories | F92: -2 | G92: 41102 | H92: 20 | I92: -65763.2 | J92: -2051.98 | K92: UK | L92: Net Banking
A93: ORD092 | B93: 45418 | C93: CUST8 | D93: Laptop | E93: Electronics | F93: 0 | G93: 3471 | H93: 0 | I93: 0 | J93: 0 | K93: Canada | L93: Debit Card
A94: ORD093 | B94: 45459 | C94: CUST16 | D94: Mouse | E94: Accessories | F94: 4 | G94: 38991 | H94: 5 | I94: 148165.8 | J94: 37658.64 | K94: UK | L94: UPI
... A101: ORD078 | B101: 45317 | C101: CUST15 | D101: Laptop | E101: Electronics | F101: 0 | G101: 33418 | H101: 20 | I101: 0 | J101: 0 | K101: India | L101: Credit Card

Sheet Cleaned_Data
A1: Order_ID | B1: Order_Date | C1: Customer_ID | D1: Product | E1: Category | F1: Quantity | G1: Unit_Price | H1: Discount_% | I1: Sales | J1: Profit | K1: Country | L1: Payment_Method | M1: Year | N1: Month | O1: Profit_Margin | P1: Month Column | Q1: Year Column | R1: Profit % Column | S1: Net Sales Column
A2: ORD001 | B2: 45414 | C2: CUST18 | D2: Mouse | E2: Accessories | F2: -1 | G2: 2139 | H2: 10 | I2: -1925.1 | J2: 3.93 | K2: India | L2: UPI | M2: 2024 | N2: 5 | O2: -0.0020414524 | P2: =TEXT(Table1[[#This Row],[Order_Date]],"mmm") -> May | Q2: =YEAR(Table1[[#This Row],[Order_Date]]) -> 2024 | R2: =Table1[[#This Row],[Profit]]/Table1[[#This Row],[Sales]] -> -0.0020414524 | S2: =IF(I2<0,0,I2) -> 0
A3: ORD002 | B3: 45342 | C3: CUST18 | D3: Phone | E3: Electronics | F3: 1 | G3: 33618 | H3: 20 | I3: 26894.4 | J3: -2403.97 | K3: UK | L3: UPI | M3: 2024 | N3: 2 | O3: -0.089385523 | P3: =TEXT(Table1[[#This Row],[Order_Date]],"mmm") -> Feb | Q3: =YEAR(Table1[[#This Row],[Order_Date]]) -> 2024 | R3: =Table1[[#This Row],[Profit]]/Table1[[#This Row],[Sales]] -> -0.089385523 | S3: =IF(I3<0,0,I3) -> 26894.4
A4: ORD003 | B4: 45378 | C4: CUST13 | D4: Phone | E4: Electronics | F4: 4 | G4: 22798 | H4: 10 | I4: 82072.8 | J4: -3103.02 | K4: UK | L4: UPI | M4: 2024 | N4: 3 | O4: -0.037808141 | P4: =TEXT(Table1[[#This Row],[Order_Date]],"mmm") -> Mar | Q4: =YEAR(Table1[[#This Row],[Order_Date]]) -> 2024 | R4: =Table1[[#This Row],[Profit]]/Table1[[#This Row],[Sales]] -> -0.037808141 | S4: =IF(I4<0,0,I4) -> 82072.8
A5: ORD004 | B5: 45447 | C5: CUST10 | D5: Mouse | E5: Accessories | F5: 5 | G5: 35642 | H5: 0 | I5: 178210 | J5: 51546.58 | K5: UK | L5: Credit Card | M5: 2024 | N5: 6 | O5: 0.28924628247573086 | P5: =TEXT(Table1[[#This Row],[Order_Date]],"mmm") -> Jun | Q5: =YEAR(Table1[[#This Row],[Order_Date]]) -> 2024 | R5: =Table1[[#This Row],[Profit]]/Table1[[#This Row],[Sales]] -> 0.28924628 | S5: =IF(I5<0,0,I5) -> 178210
A6: ORD005 | B6: 45312 | C6: CUST4 | D6: Mouse | E6: Accessories | F6: -1 | G6: 3503 | H6: 5 | I6: -3327.85 | J6: -696.28 | K6: UK | L6: Credit Card | M6: 2024 | N6: 1 | O6: 0.20922818035668675 | P6: =TEXT(Table1[[#This Row],[Order_Date]],"mmm") -> Jan | Q6: =YEAR(Table1[[#This Row],[Order_Date]]) -> 2024 | R6: =Table1[[#This Row],[Profit]]/Table1[[#This Row],[Sales]] -> 0.20922818 | S6: =IF(I6<0,0,I6) -> 0
A7: ORD006 | B7: 45466 | C7: CUST20 | D7: Headphones | E7: Accessories | F7: 3 | G7: 14230 | H7: 10 | I7: 38421 | J7: 6943.76 | K7: USA | L7: Credit Card | M7: 2024 | N7: 6 | O7: 0.1807282475729419 | P7: =TEXT(Table1[[#This Row],[Order_Date]],"mmm") -> Jun | Q7: =YEAR(Table1[[#This Row],[Order_Date]]) -> 2024 | R7: =Table1[[#This Row],[Profit]]/Table1[[#This Row],[Sales]] -> 0.18072825 | S7: =IF(I7<0,0,I7) -> 38421
A8: ORD007 | B8: 45375 | C8: CUST2 | D8: Keyboard | E8: Accessories | F8: 1 | G8: 18191 | H8: 20 | I8: 58211.2 | J8: -707.49 | K8: UK | L8: Net Banking | M8: 2024 | N8: 3 | O8: -0.012153847 | P8: =TEXT(Table1[[#This Row],[Order_Date]],"mmm") -> Mar | Q8: =YEAR(Table1[[#This Row],[Order_Date]]) -> 2024 | R8: =Table1[[#This Row],[Profit]]/Table1[[#This Row],[Sales]] -> -0.012153847 | S8: =IF(I8<0,0,I8) -> 58211.2
A9: ORD008 | B9: 45372 | C9: CUST16 | D9: Headphones | E9: Accessories | F9: -1 | G9: 14326 | H9: 20 | I9: -11460.8 | J9: -2871.47 | K9: Canada | L9: Credit Card | M9: 2024 | N9: 3 | O9: 0.2505470822281167 | P9: =TEXT(Table1[[#This Row],[Order_Date]],"mmm") -> Mar | Q9: =YEAR(Table1[[#This Row],[Order_Date]]) -> 2024 | R9: =Table1[[#This Row],[Profit]]/Table1[[#This Row],[Sales]] -> 0.25054708 | S9: =IF(I9<0,0,I9) -> 0
A10: ORD009 | B10: 45441 | C10: CUST19 | D10: Headphones | E10: Accessories | F10: 0 | G10: 16662 | H10: 20 | I10: 0 | J10: 0 | K10: USA | L10: Net Banking | M10: 2024 | N10: 5 | P10: =TEXT(Table1[[#This Row],[Order_Date]],"mmm") -> May | Q10: =YEAR(Table1[[#This Row],[Order_Date]]) -> 2024 | R10: =Table1[[#This Row],[Profit]]/Table1[[#This Row],[Sales]] -> #DIV/0! | S10: =IF(I10<0,0,I10) -> 0
A11: ORD010 | B11: 45466 | C11: CUST3 | D11: Laptop | E11: Electronics | F11: -2 | G11: 7685 | H11: 5 | I11: -14601.5 | J11: -2204.51 | K11: Canada | L11: Debit Card | M11: 2024 | N11: 6 | O11: 0.15097832414477966 | P11: =TEXT(Table1[[#This Row],[Order_Date]],"mmm") -> Jun | Q11: =YEAR(Table1[[#This Row],[Order_Date]]) -> 2024 | R11: =Table1[[#This Row],[Profit]]/Table1[[#This Row],[Sales]] -> 0.15097832 | S11: =IF(I11<0,0,I11) -> 0
A12: ORD011 | B12: 45429 | C12: CUST11 | D12: Monitor | E12: Electronics | F12: -2 | G12: 45083 | H12: 0 | I12: -90166 | J12: -15570.24 | K12: Canada | L12: UPI | M12: 2024 | N12: 5 | O12: 0.17268416032650888 | P12: =TEXT(Table1[[#This Row],[Order_Date]],"mmm") -> May | Q12: =YEAR(Table1[[#This Row],[Order_Date]]) -> 2024 | R12: =Table1[[#This Row],[Profit]]/Table1[[#This Row],[Sales]] -> 0.17268416 | S12: =IF(I12<0,0,I12) -> 0
A13: ORD012 | B13: 45319 | C13: CUST10 | D13: Mouse | E13: Accessories | F13: 2 | G13: 33306 | H13: 5 | I13: 63281.4 | J13: 6522.58 | K13: USA | L13: Credit Card | M13: 2024 | N13: 1 | O13: 0.10307262481550661 | P13: =TEXT(Table1[[#This Row],[Order_Date]],"mmm") -> Jan | Q13: =YEAR(Table1[[#This Row],[Order_Date]]) -> 2024 | R13: =Table1[[#This Row],[Profit]]/Table1[[#This Row],[Sales]] -> 0.10307262 | S13: =IF(I13<0,0,I13) -> 63281.4
A14: ORD013 | B14: 45328 | C14: CUST1 | D14: Headphones | E14: Accessories | F14: 0 | G14: 35848 | H14: 20 | I14: 0 | J14: 0 | K14: UK | L14: Credit Card | M14: 2024 | N14: 2 | P14: =TEXT(Table1[[#This Row],[Order_Date]],"mmm") -> Feb | Q14: =YEAR(Table1[[#This Row],[Order_Date]]) -> 2024 | R14: =Table1[[#This Row],[Profit]]/Table1[[#This Row],[Sales]] -> #DIV/0! | S14: =IF(I14<0,0,I14) -> 0
A15: ORD014 | B15: 45387 | C15: CUST18 | D15: Laptop | E15: Electronics | F15: 1 | G15: 37682 | H15: 0 | I15: 37682 | J15: -2477.16 | K15: Canada | L15: Credit Card | M15: 2024 | N15: 4 | O15: -0.065738549 | P15: =TEXT(Table1[[#This Row],[Order_Date]],"mmm") -> Apr | Q15: =YEAR(Table1[[#This Row],[Order_Date]]) -> 2024 | R15: =Table1[[#This Row],[Profit]]/Table1[[#This Row],[Sales]] -> -0.065738549 | S15: =IF(I15<0,0,I15) -> 37682
A16: ORD015 | B16: 45468 | C16: CUST10 | D16: Headphones | E16: Accessories | F16: 4 | G16: 14380 | H16: 20 | I16: 46016 | J16: 9300.11 | K16: UK | L16: Net Banking | M16: 2024 | N16: 6 | O16: 0.2021060066063978 | P16: =TEXT(Table1[[#This Row],[Order_Date]],"mmm") -> Jun | Q16: =YEAR(Table1[[#This Row],[Order_Date]]) -> 2024 | R16: =Table1[[#This Row],[Profit]]/Table1[[#This Row],[Sales]] -> 0.20210601 | S16: =IF(I16<0,0,I16) -> 46016
A17: ORD017 | B17: 45294 | C17: CUST16 | D17: Phone | E17: Electronics | F17: -1 | G17: 2558 | H17: 10 | I17: -2302.2 | J17: 164.97 | K17: Canada | L17: Credit Card | M17: 2024 | N17: 1 | O17: -0.071657545 | P17: =TEXT(Table1[[#This Row],[Order_Date]],"mmm") -> Jan | Q17: =YEAR(Table1[[#This Row],[Order_Date]]) -> 2024 | R17: =Table1[[#This Row],[Profit]]/Table1[[#This Row],[Sales]] -> -0.071657545 | S17: =IF(I17<0,0,I17) -> 0
A18: ORD018 | B18: 45402 | C18: CUST14 | D18: Keyboard | E18: Accessories | F18: 4 | G18: 12978 | H18: 0 | I18: 51912 | J18: -3178.45 | K18: India | L18: UPI | M18: 2024 | N18: 4 | O18: -0.061227654 | P18: =TEXT(Table1[[#This Row],[Order_Date]],"mmm") -> Apr | Q18: =YEAR(Table1[[#This Row],[Order_Date]]) -> 2024 | R18: =Table1[[#This Row],[Profit]]/Table1[[#This Row],[Sales]] -> -0.061227654 | S18: =IF(I18<0,0,I18) -> 51912
A19: ORD019 | B19: 45429 | C19: CUST14 | D19: Keyboard | E19: Accessories | F19: 3 | G19: 7661 | H19: 5 | I19: 21833.85 | J19: -510.13 | K19: India | L19: Net Banking | M19: 2024 | N19: 5 | O19: -0.02336418 | P19: =TEXT(Table1[[#This Row],[Order_Date]],"mmm") -> May | Q19: =YEAR(Table1[[#This Row],[Order_Date]]) -> 2024 | R19: =Table1[[#This Row],[Profit]]/Table1[[#This Row],[Sales]] -> -0.02336418 | S19: =IF(I19<0,0,I19) -> 21833.85
A20: ORD020 | B20: 45315 | C20: CUST8 | D20: Monitor | E20: Electronics | F20: -1 | G20: 3815 | H20: 20 | I20: -3052 | J20: -715.42 | K20: USA | L20: Net Banking | M20: 2024 | N20: 1 | O20: 0.2344102228047182 | P20: =TEXT(Table1[[#This Row],[Order_Date]],"mmm") -> Jan | Q20: =YEAR(Table1[[#This Row],[Order_Date]]) -> 2024 | R20: =Table1[[#This Row],[Profit]]/Table1[[#This Row],[Sales]] -> 0.23441022 | S20: =IF(I20<0,0,I20) -> 0
A21: ORD021 | B21: 45507 | C21: CUST15 | D21: Laptop | E21: Electronics | F21: 0 | G21: 25336 | H21: 0 | I21: 0 | J21: 0 | K21: Canada | L21: Credit Card | M21: 2024 | N21: 8 | P21: =TEXT(Table1[[#This Row],[Order_Date]],"mmm") -> Aug | Q21: =YEAR(Table1[[#This Row],[Order_Date]]) -> 2024 | R21: =Table1[[#This Row],[Profit]]/Table1[[#This Row],[Sales]] -> #DIV/0! | S21: =IF(I21<0,0,I21) -> 0
A22: ORD022 | B22: 45430 | C22: CUST11 | D22: Phone | E22: Electronics | F22: 2 | G22: 14767 | H22: 0 | I22: 29534 | J22: 3888.8 | K22: USA | L22: UPI | M22: 2024 | N22: 5 | O22: 0.13167197128732985 | P22: =TEXT(Table1[[#This Row],[Order_Date]],"mmm") -> May | Q22: =YEAR(Table1[[#This Row],[Order_Date]]) -> 2024 | R22: =Table1[[#This Row],[Profit]]/Table1[[#This Row],[Sales]] -> 0.13167197 | S22: =IF(I22<0,0,I22) -> 29534
A23: ORD023 | B23: 45464 | C23: CUST13 | D23: Monitor | E23: Electronics | F23: -1 | G23: 12678 | H23: 0 | I23: -12678 | J23: -1749.74 | K23: USA | L23: UPI | M23: 2024 | N23: 6 | O23: 0.13801388231582268 | P23: =TEXT(Table1[[#This Row],[Order_Date]],"mmm") -> Jun | Q23: =YEAR(Table1[[#This Row],[Order_Date]]) -> 2024 | R23: =Table1[[#This Row],[Profit]]/Table1[[#This Row],[Sales]] -> 0.13801388 | S23: =IF(I23<0,0,I23) -> 0
A24: ORD024 | B24: 45372 | C24: CUST7 | D24: Monitor | E24: Electronics | F24: -1 | G24: 27974 | H24: 20 | I24: -22379.2 | J24: -2821.81 | K24: UK | L24: Net Banking | M24: 2024 | N24: 3 | O24: 0.12609074497747907 | P24: =TEXT(Table1[[#This Row],[Order_Date]],"mmm") -> Mar | Q24: =YEAR(Table1[[#This Row],[Order_Date]]) -> 2024 | R24: =Table1[[#This Row],[Profit]]/Table1[[#This Row],[Sales]] -> 0.12609074 | S24: =IF(I24<0,0,I24) -> 0
A25: ORD026 | B25: 45354 | C25: CUST6 | D25: Monitor | E25: Electronics | F25: 2 | G25: 9180 | H25: 10 | I25: 16524 | J25: 4169.76 | K25: UK | L25: UPI | M25: 2024 | N25: 3 | O25: 0.25234567901234567 | P25: =TEXT(Table1[[#This Row],[Order_Date]],"mmm") -> Mar | Q25: =YEAR(Table1[[#This Row],[Order_Date]]) -> 2024 | R25: =Table1[[#This Row],[Profit]]/Table1[[#This Row],[Sales]] -> 0.25234568 | S25: =IF(I25<0,0,I25) -> 16524
A26: ORD027 | B26: 45384 | C26: CUST4 | D26: Mouse | E26: Accessories | F26: 2 | G26: 43975 | H26: 0 | I26: 87950 | J26: 24236.56 | K26: UK | L26: Credit Card | M26: 2024 | N26: 4 | O26: 0.2755720295622513 | P26: =TEXT(Table1[[#This Row],[Order_Date]],"mmm") -> Apr | Q26: =YEAR(Table1[[#This Row],[Order_Date]]) -> 2024 | R26: =Table1[[#This Row],[Profit]]/Table1[[#This Row],[Sales]] -> 0.27557203 | S26: =IF(I26<0,0,I26) -> 87950
A27: ORD028 | B27: 45415 | C27: CUST2 | D27: Mouse | E27: Accessories | F27: 3 | G27: 13842 | H27: 10 | I27: 37373.4 | J27: 3818.2 | K27: UK | L27: UPI | M27: 2024 | N27: 5 | O27: 0.10216357088196416 | P27: =TEXT(Table1[[#This Row],[Order_Date]],"mmm") -> May | Q27: =YEAR(Table1[[#This Row],[Order_Date]]) -> 2024 | R27: =Table1[[#This Row],[Profit]]/Table1[[#This Row],[Sales]] -> 0.10216357 | S27: =IF(I27<0,0,I27) -> 37373.4
A28: ORD029 | B28: 45405 | C28: CUST14 | D28: Laptop | E28: Electronics | F28: 3 | G28: 9073 | H28: 10 | I28: 24497.1 | J28: -866.39 | K28: USA | L28: UPI | M28: 2024 | N28: 4 | O28: -0.035367043 | P28: =TEXT(Table1[[#This Row],[Order_Date]],"mmm") -> Apr | Q28: =YEAR(Table1[[#This Row],[Order_Date]]) -> 2024 | R28: =Table1[[#This Row],[Profit]]/Table1[[#This Row],[Sales]] -> -0.035367043 | S28: =IF(I28<0,0,I28) -> 24497.1
A29: ORD030 | B29: 45355 | C29: CUST2 | D29: Headphones | E29: Accessories | F29: 0 | G29: 28666 | H29: 5 | I29: 0 | J29: 0 | K29: USA | L29: UPI | M29: 2024 | N29: 3 | P29: =TEXT(Table1[[#This Row],[Order_Date]],"mmm") -> Mar | Q29: =YEAR(Table1[[#This Row],[Order_Date]]) -> 2024 | R29: =Table1[[#This Row],[Profit]]/Table1[[#This Row],[Sales]] -> #DIV/0! | S29: =IF(I29<0,0,I29) -> 0
A30: ORD031 | B30: 45294 | C30: CUST6 | D30: Headphones | E30: Accessories | F30: 1 | G30: 41175 | H30: 5 | I30: 156465 | J30: 42293.35 | K30: UK | L30: Net Banking | M30: 2024 | N30: 1 | O30: 0.27030549963250566 | P30: =TEXT(Table1[[#This Row],[Order_Date]],"mmm") -> Jan | Q30: =YEAR(Table1[[#This Row],[Order_Date]]) -> 2024 | R30: =Table1[[#This Row],[Profit]]/Table1[[#This Row],[Sales]] -> 0.2703055 | S30: =IF(I30<0,0,I30) -> 156465
A31: ORD032 | B31: 45319 | C31: CUST2 | D31: Mouse | E31: Accessories | F31: 1 | G31: 17985 | H31: 5 | I31: 17085.75 | J31: 3672.58 | K31: Canada | L31: Debit Card | M31: 2024 | N31: 1 | O31: 0.21494988513819996 | P31: =TEXT(Table1[[#This Row],[Order_Date]],"mmm") -> Jan | Q31: =YEAR(Table1[[#This Row],[Order_Date]]) -> 2024 | R31: =Table1[[#This Row],[Profit]]/Table1[[#This Row],[Sales]] -> 0.21494989 | S31: =IF(I31<0,0,I31) -> 17085.75
A32: ORD033 | B32: 45630 | C32: CUST3 | D32: Headphones | E32: Accessories | F32: 1 | G32: 15109 | H32: 0 | I32: 15109 | J32: 2478.08 | K32: Canada | L32: Debit Card | M32: 2024 | N32: 12 | O32: 0.16401350188629293 | P32: =TEXT(Table1[[#This Row],[Order_Date]],"mmm") -> Dec | Q32: =YEAR(Table1[[#This Row],[Order_Date]]) -> 2024 | R32: =Table1[[#This Row],[Profit]]/Table1[[#This Row],[Sales]] -> 0.1640135 | S32: =IF(I32<0,0,I32) -> 15109
A33: ORD035 | B33: 45627 | C33: CUST1 | D33: Monitor | E33: Electronics | F33: -1 | G33: 25744 | H33: 20 | I33: -20595.2 | J33: 493.64 | K33: USA | L33: Debit Card | M33: 2024 | N33: 12 | O33: -0.023968692 | P33: =TEXT(Table1[[#This Row],[Order_Date]],"mmm") -> Dec | Q33: =YEAR(Table1[[#This Row],[Order_Date]]) -> 2024 | R33: =Table1[[#This Row],[Profit]]/Table1[[#This Row],[Sales]] -> -0.023968692 | S33: =IF(I33<0,0,I33) -> 0
A34: ORD036 | B34: 45461 | C34: CUST10 | D34: Keyboard | E34: Accessories | F34: -1 | G34: 44031 | H34: 10 | I34: -39627.9 | J34: -5914.95 | K34: UK | L34: Net Banking | M34: 2024 | N34: 6 | O34: 0.14926226219406025 | P34: =TEXT(Table1[[#This Row],[Order_Date]],"mmm") -> Jun | Q34: =YEAR(Table1[[#This Row],[Order_Date]]) -> 2024 | R34: =Table1[[#This Row],[Profit]]/Table1[[#This Row],[Sales]] -> 0.14926226 | S34: =IF(I34<0,0,I34) -> 0
A35: ORD037 | B35: 45462 | C35: CUST6 | D35: Mouse | E35: Accessories | F35: 2 | G35: 36833 | H35: 5 | I35: 69982.7 | J35: -1628.07 | K35: India | L35: Debit Card | M35: 2024 | N35: 6 | O35: -0.023263892 | P35: =TEXT(Table1[[#This Row],[Order_Date]],"mmm") -> Jun | Q35: =YEAR(Table1[[#This Row],[Order_Date]]) -> 2024 | R35: =Table1[[#This Row],[Profit]]/Table1[[#This Row],[Sales]] -> -0.023263892 | S35: =IF(I35<0,0,I35) -> 69982.7
A36: ORD038 | B36: 45374 | C36: CUST15 | D36: Headphones | E36: Accessories | F36: 1 | G36: 28673 | H36: 20 | I36: 22938.4 | J36: 3272.5 | K36: USA | L36: UPI | M36: 2024 | N36: 3 | O36: 0.14266470198444528 | P36: =TEXT(Table1[[#This Row],[Order_Date]],"mmm") -> Mar | Q36: =YEAR(Table1[[#This Row],[Order_Date]]) -> 2024 | R36: =Table1[[#This Row],[Profit]]/Table1[[#This Row],[Sales]] -> 0.1426647 | S36: =IF(I36<0,0,I36) -> 22938.4
A37: ORD039 | B37: 45349 | C37: CUST5 | D37: Headphones | E37: Electronics | F37: 3 | G37: 6620 | H37: 5 | I37: 18867 | J37: 3190.75 | K37: Canada | L37: UPI | M37: 2024 | N37: 2 | O37: 0.1691180367838024 | P37: =TEXT(Table1[[#This Row],[Order_Date]],"mmm") -> Feb | Q37: =YEAR(Table1[[#This Row],[Order_Date]]) -> 2024 | R37: =Table1[[#This Row],[Profit]]/Table1[[#This Row],[Sales]] -> 0.16911804 | S37: =IF(I37<0,0,I37) -> 18867
A38: ORD040 | B38: 45470 | C38: CUST13 | D38: Keyboard | E38: Accessories | F38: 4 | G38: 41772 | H38: 20 | I38: 133670.4 | J38: -2970.95 | K38: India | L38: UPI | M38: 2024 | N38: 6 | O38: -0.022225938 | P38: =TEXT(Table1[[#This Row],[Order_Date]],"mmm") -> Jun | Q38: =YEAR(Table1[[#This Row],[Order_Date]]) -> 2024 | R38: =Table1[[#This Row],[Profit]]/Table1[[#This Row],[Sales]] -> -0.022225938 | S38: =IF(I38<0,0,I38) -> 133670.4
A39: ORD041 | B39: 45434 | C39: CUST4 | D39: Keyboard | E39: Accessories | F39: 1 | G39: 12026 | H39: 20 | I39: 9620.8 | J39: 825.66 | K39: UK | L39: Net Banking | M39: 2024 | N39: 5 | O39: 0.085820306 | P39: =TEXT(Table1[[#This Row],[Order_Date]],"mmm") -> May | Q39: =YEAR(Table1[[#This Row],[Order_Date]]) -> 2024 | R39: =Table1[[#This Row],[Profit]]/Table1[[#This Row],[Sales]] -> 0.085820306 | S39: =IF(I39<0,0,I39) -> 9620.8
A40: ORD042 | B40: 45296 | C40: CUST8 | D40: Monitor | E40: Electronics | F40: 4 | G40: 36405 | H40: 15 | I40: 123777 | J40: 32043.79 | K40: Canada | L40: Credit Card | M40: 2024 | N40: 1 | O40: 0.2588832335571229 | P40: =TEXT(Table1[[#This Row],[Order_Date]],"mmm") -> Jan | Q40: =YEAR(Table1[[#This Row],[Order_Date]]) -> 2024 | R40: =Table1[[#This Row],[Profit]]/Table1[[#This Row],[Sales]] -> 0.25888323 | S40: =IF(I40<0,0,I40) -> 123777
A41: ORD043 | B41: 45377 | C41: CUST18 | D41: Headphones | E41: Accessories | F41: 5 | G41: 5577 | H41: 10 | I41: 25096.5 | J41: -155.66 | K41: Canada | L41: Credit Card | M41: 2024 | N41: 3 | O41: -0.0062024585 | P41: =TEXT(Table1[[#This Row],[Order_Date]],"mmm") -> Mar | Q41: =YEAR(Table1[[#This Row],[Order_Date]]) -> 2024 | R41: =Table1[[#This Row],[Profit]]/Table1[[#This Row],[Sales]] -> -0.0062024585 | S41: =IF(I41<0,0,I41) -> 25096.5
A42: ORD044 | B42: 45430 | C42: CUST2 | D42: Mouse | E42: Accessories | F42: 1 | G42: 4709 | H42: 15 | I42: 4002.65 | J42: 252.33 | K42: India | L42: Net Banking | M42: 2024 | N42: 5 | O42: 0.063040736 | P42: =TEXT(Table1[[#This Row],[Order_Date]],"mmm") -> May | Q42: =YEAR(Table1[[#This Row],[Order_Date]]) -> 2024 | R42: =Table1[[#This Row],[Profit]]/Table1[[#This Row],[Sales]] -> 0.063040736 | S42: =IF(I42<0,0,I42) -> 4002.65
A43: ORD045 | B43: 45399 | C43: CUST18 | D43: Keyboard | E43: Accessories | F43: -2 | G43: 23552 | H43: 10 | I43: -42393.6 | J43: -8537.65 | K43: Canada | L43: Credit Card | M43: 2024 | N43: 4 | O43: 0.20139006831219808 | P43: =TEXT(Table1[[#This Row],[Order_Date]],"mmm") -> Apr | Q43: =YEAR(Table1[[#This Row],[Order_Date]]) -> 2024 | R43: =Table1[[#This Row],[Profit]]/Table1[[#This Row],[Sales]] -> 0.20139007 | S43: =IF(I43<0,0,I43) -> 0
A44: ORD046 | B44: 45463 | C44: CUST13 | D44: Headphones | E44: Accessories | F44: 4 | G44: 32327 | H44: 0 | I44: 129308 | J44: 7182.14 | K44: USA | L44: UPI | M44: 2024 | N44: 6 | O44: 0.05554289 | P44: =TEXT(Table1[[#This Row],[Order_Date]],"mmm") -> Jun | Q44: =YEAR(Table1[[#This Row],[Order_Date]]) -> 2024 | R44: =Table1[[#This Row],[Profit]]/Table1[[#This Row],[Sales]] -> 0.05554289 | S44: =IF(I44<0,0,I44) -> 129308
A45: ORD047 | B45: 45410 | C45: CUST9 | D45: Keyboard | E45: Accessories | F45: -2 | G45: 6001 | H45: 15 | I45: -10201.7 | J45: 466.42 | K45: UK | L45: Debit Card | M45: 2024 | N45: 4 | O45: -0.045719831 | P45: =TEXT(Table1[[#This Row],[Order_Date]],"mmm") -> Apr | Q45: =YEAR(Table1[[#This Row],[Order_Date]]) -> 2024 | R45: =Table1[[#This Row],[Profit]]/Table1[[#This Row],[Sales]] -> -0.045719831 | S45: =IF(I45<0,0,I45) -> 0
A46: ORD048 | B46: 45312 | C46: CUST18 | D46: Keyboard | E46: Accessories | F46: 2 | G46: 49783 | H46: 15 | I46: 84631.1 | J46: 76.9 | K46: USA | L46: UPI | M46: 2024 | N46: 1 | O46: 0.00090864942 | P46: =TEXT(Table1[[#This Row],[Order_Date]],"mmm") -> Jan | Q46: =YEAR(Table1[[#This Row],[Order_Date]]) -> 2024 | R46: =Table1[[#This Row],[Profit]]/Table1[[#This Row],[Sales]] -> 0.00090864942 | S46: =IF(I46<0,0,I46) -> 84631.1
A47: ORD049 | B47: 45343 | C47: CUST20 | D47: Mouse | E47: Accessories | F47: -2 | G47: 49929 | H47: 0 | I47: -99858 | J47: -27944.73 | K47: India | L47: Credit Card | M47: 2024 | N47: 2 | O47: 0.2798446794448116 | P47: =TEXT(Table1[[#This Row],[Order_Date]],"mmm") -> Feb | Q47: =YEAR(Table1[[#This Row],[Order_Date]]) -> 2024 | R47: =Table1[[#This Row],[Profit]]/Table1[[#This Row],[Sales]] -> 0.27984468 | S47: =IF(I47<0,0,I47) -> 0
A48: ORD050 | B48: 45321 | C48: CUST6 | D48: Keyboard | E48: Accessories | F48: 2 | G48: 24675 | H48: 5 | I48: 46882.5 | J48: 6674.06 | K48: India | L48: Debit Card | M48: 2024 | N48: 1 | O48: 0.14235716951954355 | P48: =TEXT(Table1[[#This Row],[Order_Date]],"mmm") -> Jan | Q48: =YEAR(Table1[[#This Row],[Order_Date]]) -> 2024 | R48: =Table1[[#This Row],[Profit]]/Table1[[#This Row],[Sales]] -> 0.14235717 | S48: =IF(I48<0,0,I48) -> 46882.5
A49: ORD051 | B49: 45468 | C49: CUST8 | D49: Monitor | E49: Electronics | F49: 4 | G49: 26495 | H49: 5 | I49: 100681 | J49: -7007.54 | K49: India | L49: UPI | M49: 2024 | N49: 6 | O49: -0.069601414 | P49: =TEXT(Table1[[#This Row],[Order_Date]],"mmm") -> Jun | Q49: =YEAR(Table1[[#This Row],[Order_Date]]) -> 2024 | R49: =Table1[[#This Row],[Profit]]/Table1[[#This Row],[Sales]] -> -0.069601414 | S49: =IF(I49<0,0,I49) -> 100681
A50: ORD052 | B50: 45457 | C50: CUST14 | D50: Headphones | E50: Accessories | F50: 4 | G50: 43853 | H50: 10 | I50: 157870.8 | J50: -11432.58 | K50: UK | L50: Net Banking | M50: 2024 | N50: 6 | O50: -0.072417318 | P50: =TEXT(Table1[[#This Row],[Order_Date]],"mmm") -> Jun | Q50: =YEAR(Table1[[#This Row],[Order_Date]]) -> 2024 | R50: =Table1[[#This Row],[Profit]]/Table1[[#This Row],[Sales]] -> -0.072417318 | S50: =IF(I50<0,0,I50) -> 157870.8
A51: ORD053 | B51: 45458 | C51: CUST18 | D51: Mouse | E51: Accessories | F51: 0 | G51: 29040 | H51: 5 | I51: 0 | J51: 0 | K51: UK | L51: Debit Card | M51: 2024 | N51: 6 | P51: =TEXT(Table1[[#This Row],[Order_Date]],"mmm") -> Jun | Q51: =YEAR(Table1[[#This Row],[Order_Date]]) -> 2024 | R51: =Table1[[#This Row],[Profit]]/Table1[[#This Row],[Sales]] -> #DIV/0! | S51: =IF(I51<0,0,I51) -> 0
A52: ORD054 | B52: 45410 | C52: CUST13 | D52: Phone | E52: Electronics | F52: -1 | G52: 18779 | H52: 15 | I52: -15962.15 | J52: 39.18 | K52: UK | L52: Credit Card | M52: 2024 | N52: 4 | O52: -0.0024545566 | P52: =TEXT(Table1[[#This Row],[Order_Date]],"mmm") -> Apr | Q52: =YEAR(Table1[[#This Row],[Order_Date]]) -> 2024 | R52: =Table1[[#This Row],[Profit]]/Table1[[#This Row],[Sales]] -> -0.0024545566 | S52: =IF(I52<0,0,I52) -> 0
A53: ORD055 | B53: 45297 | C53: CUST9 | D53: Keyboard | E53: Accessories | F53: 1 | G53: 23753 | H53: 10 | I53: 21377.7 | J53: 772.49 | K53: USA | L53: UPI | M53: 2024 | N53: 1 | O53: 0.036135318579641404 | P53: =TEXT(Table1[[#This Row],[Order_Date]],"mmm") -> Jan | Q53: =YEAR(Table1[[#This Row],[Order_Date]]) -> 2024 | R53: =Table1[[#This Row],[Profit]]/Table1[[#This Row],[Sales]] -> 0.036135319 | S53: =IF(I53<0,0,I53) -> 21377.7
A54: ORD056 | B54: 45468 | C54: CUST16 | D54: Phone | E54: Electronics | F54: 1 | G54: 32519 | H54: 20 | I54: 104060.8 | J54: 21152.01 | K54: UK | L54: Credit Card | M54: 2024 | N54: 6 | O54: 0.2032658791783265 | P54: =TEXT(Table1[[#This Row],[Order_Date]],"mmm") -> Jun | Q54: =YEAR(Table1[[#This Row],[Order_Date]]) -> 2024 | R54: =Table1[[#This Row],[Profit]]/Table1[[#This Row],[Sales]] -> 0.20326588 | S54: =IF(I54<0,0,I54) -> 104060.8
A55: ORD057 | B55: 45433 | C55: CUST14 | D55: Keyboard | E55: Accessories | F55: 1 | G55: 20567 | H55: 20 | I55: 16453.6 | J55: 783.33 | K55: UK | L55: Net Banking | M55: 2024 | N55: 5 | O55: 0.047608426 | P55: =TEXT(Table1[[#This Row],[Order_Date]],"mmm") -> May | Q55: =YEAR(Table1[[#This Row],[Order_Date]]) -> 2024 | R55: =Table1[[#This Row],[Profit]]/Table1[[#This Row],[Sales]] -> 0.047608426 | S55: =IF(I55<0,0,I55) -> 16453.6
A56: ORD058 | B56: 45341 | C56: CUST18 | D56: Headphones | E56: Accessories | F56: 2 | G56: 16975 | H56: 5 | I56: 32252.5 | J56: -1668.67 | K56: USA | L56: Credit Card | M56: 2024 | N56: 2 | O56: -0.051737695 | P56: =TEXT(Table1[[#This Row],[Order_Date]],"mmm") -> Feb | Q56: =YEAR(Table1[[#This Row],[Order_Date]]) -> 2024 | R56: =Table1[[#This Row],[Profit]]/Table1[[#This Row],[Sales]] -> -0.051737695 | S56: =IF(I56<0,0,I56) -> 32252.5
A57: ORD059 | B57: 45426 | C57: CUST4 | D57: Mouse | E57: Accessories | F57: 5 | G57: 18620 | H57: 20 | I57: 74480 | J57: 21647.08 | K57: UK | L57: Credit Card | M57: 2024 | N57: 5 | O57: 0.29064285714285715 | P57: =TEXT(Table1[[#This Row],[Order_Date]],"mmm") -> May | Q57: =YEAR(Table1[[#This Row],[Order_Date]]) -> 2024 | R57: =Table1[[#This Row],[Profit]]/Table1[[#This Row],[Sales]] -> 0.29064286 | S57: =IF(I57<0,0,I57) -> 74480
A58: ORD060 | B58: 45627 | C58: CUST18 | D58: Headphones | E58: Accessories | F58: -2 | G58: 46900 | H58: 20 | I58: -75040 | J58: 3704.49 | K58: Canada | L58: UPI | M58: 2024 | N58: 12 | O58: -0.049366871 | P58: =TEXT(Table1[[#This Row],[Order_Date]],"mmm") -> Dec | Q58: =YEAR(Table1[[#This Row],[Order_Date]]) -> 2024 | R58: =Table1[[#This Row],[Profit]]/Table1[[#This Row],[Sales]] -> -0.049366871 | S58: =IF(I58<0,0,I58) -> 0
A59: ORD061 | B59: 45339 | C59: CUST9 | D59: Laptop | E59: Electronics | F59: 2 | G59: 31262 | H59: 15 | I59: 53145.4 | J59: 4049.02 | K59: India | L59: Net Banking | M59: 2024 | N59: 2 | O59: 0.076187591 | P59: =TEXT(Table1[[#This Row],[Order_Date]],"mmm") -> Feb | Q59: =YEAR(Table1[[#This Row],[Order_Date]]) -> 2024 | R59: =Table1[[#This Row],[Profit]]/Table1[[#This Row],[Sales]] -> 0.076187591 | S59: =IF(I59<0,0,I59) -> 53145.4
A60: ORD062 | B60: 45436 | C60: CUST3 | D60: Keyboard | E60: Accessories | F60: -1 | G60: 38315 | H60: 0 | I60: -38315 | J60: 1506.13 | K60: Canada | L60: Credit Card | M60: 2024 | N60: 5 | O60: -0.039309148 | P60: =TEXT(Table1[[#This Row],[Order_Date]],"mmm") -> May | Q60: =YEAR(Table1[[#This Row],[Order_Date]]) -> 2024 | R60: =Table1[[#This Row],[Profit]]/Table1[[#This Row],[Sales]] -> -0.039309148 | S60: =IF(I60<0,0,I60) -> 0
A61: ORD063 | B61: 45442 | C61: CUST10 | D61: Monitor | E61: Electronics | F61: 4 | G61: 30024 | H61: 15 | I61: 102081.6 | J61: 1933.55 | K61: India | L61: Credit Card | M61: 2024 | N61: 5 | O61: 0.018941219573360916 | P61: =TEXT(Table1[[#This Row],[Order_Date]],"mmm") -> May | Q61: =YEAR(Table1[[#This Row],[Order_Date]]) -> 2024 | R61: =Table1[[#This Row],[Profit]]/Table1[[#This Row],[Sales]] -> 0.01894122 | S61: =IF(I61<0,0,I61) -> 102081.6
A62: ORD064 | B62: 45336 | C62: CUST6 | D62: Mouse | E62: Electronics | F62: 1 | G62: 17843 | H62: 0 | I62: 17843 | J62: -663.35 | K62: Canada | L62: Debit Card | M62: 2024 | N62: 2 | O62: -0.037177044 | P62: =TEXT(Table1[[#This Row],[Order_Date]],"mmm") -> Feb | Q62: =YEAR(Table1[[#This Row],[Order_Date]]) -> 2024 | R62: =Table1[[#This Row],[Profit]]/Table1[[#This Row],[Sales]] -> -0.037177044 | S62: =IF(I62<0,0,I62) -> 17843
A63: ORD065 | B63: 45408 | C63: CUST8 | D63: Laptop | E63: Electronics | F63: 1 | G63: 19381 | H63: 10 | I63: 17442.9 | J63: 3160.57 | K63: USA | L63: Net Banking | M63: 2024 | N63: 4 | O63: 0.18119521409857306 | P63: =TEXT(Table1[[#This Row],[Order_Date]],"mmm") -> Apr | Q63: =YEAR(Table1[[#This Row],[Order_Date]]) -> 2024 | R63: =Table1[[#This Row],[Profit]]/Table1[[#This Row],[Sales]] -> 0.18119521 | S63: =IF(I63<0,0,I63) -> 17442.9
A64: ORD066 | B64: 45445 | C64: CUST6 | D64: Laptop | E64: Electronics | F64: 1 | G64: 42943 | H64: 5 | I64: 40795.85 | J64: 10744.18 | K64: UK | L64: Net Banking | M64: 2024 | N64: 6 | O64: 0.2633645334022946 | P64: =TEXT(Table1[[#This Row],[Order_Date]],"mmm") -> Jun | Q64: =YEAR(Table1[[#This Row],[Order_Date]]) -> 2024 | R64: =Table1[[#This Row],[Profit]]/Table1[[#This Row],[Sales]] -> 0.26336453 | S64: =IF(I64<0,0,I64) -> 40795.85
A65: ORD067 | B65: 45568 | C65: CUST16 | D65: Laptop | E65: Electronics | F65: 5 | G65: 45633 | H65: 10 | I65: 205348.5 | J65: 36940.86 | K65: Canada | L65: Debit Card | M65: 2024 | N65: 10 | O65: 0.17989349812635594 | P65: =TEXT(Table1[[#This Row],[Order_Date]],"mmm") -> Oct | Q65: =YEAR(Table1[[#This Row],[Order_Date]]) -> 2024 | R65: =Table1[[#This Row],[Profit]]/Table1[[#This Row],[Sales]] -> 0.1798935 | S65: =IF(I65<0,0,I65) -> 205348.5
A66: ORD068 | B66: 45464 | C66: CUST19 | D66: Monitor | E66: Electronics | F66: 1 | G66: 2195 | H66: 0 | I66: 4390 | J66: -37.01 | K66: UK | L66: UPI | M66: 2024 | N66: 6 | O66: -0.0084305239 | P66: =TEXT(Table1[[#This Row],[Order_Date]],"mmm") -> Jun | Q66: =YEAR(Table1[[#This Row],[Order_Date]]) -> 2024 | R66: =Table1[[#This Row],[Profit]]/Table1[[#This Row],[Sales]] -> -0.0084305239 | S66: =IF(I66<0,0,I66) -> 4390
A67: ORD069 | B67: 45338 | C67: CUST14 | D67: Phone | E67: Electronics | F67: 5 | G67: 34510 | H67: 15 | I67: 146667.5 | J67: 39076.49 | K67: India | L67: Net Banking | M67: 2024 | N67: 2 | O67: 0.2664291 | P67: =TEXT(Table1[[#This Row],[Order_Date]],"mmm") -> Feb | Q67: =YEAR(Table1[[#This Row],[Order_Date]]) -> 2024 | R67: =Table1[[#This Row],[Profit]]/Table1[[#This Row],[Sales]] -> 0.2664291 | S67: =IF(I67<0,0,I67) -> 146667.5
A68: ORD070 | B68: 45598 | C68: CUST16 | D68: Headphones | E68: Accessories | F68: 4 | G68: 22343 | H68: 10 | I68: 80434.8 | J68: 13517.34 | K68: India | L68: Net Banking | M68: 2024 | N68: 11 | O68: 0.1680533798803503 | P68: =TEXT(Table1[[#This Row],[Order_Date]],"mmm") -> Nov | Q68: =YEAR(Table1[[#This Row],[Order_Date]]) -> 2024 | R68: =Table1[[#This Row],[Profit]]/Table1[[#This Row],[Sales]] -> 0.16805338 | S68: =IF(I68<0,0,I68) -> 80434.8
A69: ORD071 | B69: 45395 | C69: CUST1 | D69: Laptop | E69: Electronics | F69: 3 | G69: 17041 | H69: 10 | I69: 46010.7 | J69: -2467.62 | K69: Canada | L69: UPI | M69: 2024 | N69: 4 | O69: -0.053631438 | P69: =TEXT(Table1[[#This Row],[Order_Date]],"mmm") -> Apr | Q69: =YEAR(Table1[[#This Row],[Order_Date]]) -> 2024 | R69: =Table1[[#This Row],[Profit]]/Table1[[#This Row],[Sales]] -> -0.053631438 | S69: =IF(I69<0,0,I69) -> 46010.7
A70: ORD072 | B70: 45305 | C70: CUST18 | D70: Phone | E70: Electronics | F70: 3 | G70: 41304 | H70: 15 | I70: 105325.2 | J70: 15816 | K70: Canada | L70: UPI | M70: 2024 | N70: 1 | O70: 0.15016349363685044 | P70: =TEXT(Table1[[#This Row],[Order_Date]],"mmm") -> Jan | Q70: =YEAR(Table1[[#This Row],[Order_Date]]) -> 2024 | R70: =Table1[[#This Row],[Profit]]/Table1[[#This Row],[Sales]] -> 0.15016349 | S70: =IF(I70<0,0,I70) -> 105325.2
A71: ORD073 | B71: 45383 | C71: CUST3 | D71: Laptop | E71: Electronics | F71: 1 | G71: 47016 | H71: 5 | I71: 44665.2 | J71: 1085.37 | K71: India | L71: Net Banking | M71: 2024 | N71: 4 | O71: 0.024300126272802987 | P71: =TEXT(Table1[[#This Row],[Order_Date]],"mmm") -> Apr | Q71: =YEAR(Table1[[#This Row],[Order_Date]]) -> 2024 | R71: =Table1[[#This Row],[Profit]]/Table1[[#This Row],[Sales]] -> 0.024300126 | S71: =IF(I71<0,0,I71) -> 44665.2
A72: ORD074 | B72: 45568 | C72: CUST16 | D72: Laptop | E72: Electronics | F72: 0 | G72: 33161 | H72: 10 | I72: 0 | J72: 0 | K72: USA | L72: Net Banking | M72: 2024 | N72: 10 | P72: =TEXT(Table1[[#This Row],[Order_Date]],"mmm") -> Oct | Q72: =YEAR(Table1[[#This Row],[Order_Date]]) -> 2024 | R72: =Table1[[#This Row],[Profit]]/Table1[[#This Row],[Sales]] -> #DIV/0! | S72: =IF(I72<0,0,I72) -> 0
A73: ORD075 | B73: 45398 | C73: CUST17 | D73: Phone | E73: Electronics | F73: 1 | G73: 5075 | H73: 10 | I73: 0 | J73: 0 | K73: UK | L73: Net Banking | M73: 2024 | N73: 4 | P73: =TEXT(Table1[[#This Row],[Order_Date]],"mmm") -> Apr | Q73: =YEAR(Table1[[#This Row],[Order_Date]]) -> 2024 | R73: =Table1[[#This Row],[Profit]]/Table1[[#This Row],[Sales]] -> #DIV/0! | S73: =IF(I73<0,0,I73) -> 0
A74: ORD076 | B74: 45433 | C74: CUST13 | D74: Phone | E74: Electronics | F74: 5 | G74: 35796 | H74: 15 | I74: 152133 | J74: 5788.6 | K74: USA | L74: Credit Card | M74: 2024 | N74: 5 | O74: 0.038049601335673394 | P74: =TEXT(Table1[[#This Row],[Order_Date]],"mmm") -> May | Q74: =YEAR(Table1[[#This Row],[Order_Date]]) -> 2024 | R74: =Table1[[#This Row],[Profit]]/Table1[[#This Row],[Sales]] -> 0.038049601 | S74: =IF(I74<0,0,I74) -> 152133
A75: ORD077 | B75: 45296 | C75: CUST13 | D75: Monitor | E75: Electronics | F75: 4 | G75: 15806 | H75: 15 | I75: 53740.4 | J75: -4435.79 | K75: USA | L75: Net Banking | M75: 2024 | N75: 1 | O75: -0.082541068 | P75: =TEXT(Table1[[#This Row],[Order_Date]],"mmm") -> Jan | Q75: =YEAR(Table1[[#This Row],[Order_Date]]) -> 2024 | R75: =Table1[[#This Row],[Profit]]/Table1[[#This Row],[Sales]] -> -0.082541068 | S75: =IF(I75<0,0,I75) -> 53740.4
A76: ORD078 | B76: 45317 | C76: CUST15 | D76: Laptop | E76: Electronics | F76: 0 | G76: 33418 | H76: 20 | I76: 0 | J76: 0 | K76: India | L76: Credit Card | M76: 2024 | N76: 1 | P76: =TEXT(Table1[[#This Row],[Order_Date]],"mmm") -> Jan | Q76: =YEAR(Table1[[#This Row],[Order_Date]]) -> 2024 | R76: =Table1[[#This Row],[Profit]]/Table1[[#This Row],[Sales]] -> #DIV/0! | S76: =IF(I76<0,0,I76) -> 0
A77: ORD079 | B77: 45507 | C77: CUST13 | D77: Keyboard | E77: Accessories | F77: 0 | G77: 5403 | H77: 15 | I77: 0 | J77: 0 | K77: Canada | L77: Debit Card | M77: 2024 | N77: 8 | P77: =TEXT(Table1[[#This Row],[Order_Date]],"mmm") -> Aug | Q77: =YEAR(Table1[[#This Row],[Order_Date]]) -> 2024 | R77: =Table1[[#This Row],[Profit]]/Table1[[#This Row],[Sales]] -> #DIV/0! | S77: =IF(I77<0,0,I77) -> 0
A78: ORD080 | B78: 45294 | C78: CUST10 | D78: Mouse | E78: Accessories | F78: 5 | G78: 35956 | H78: 0 | I78: 179780 | J78: 26424.74 | K78: Canada | L78: UPI | M78: 2024 | N78: 1 | O78: 0.14698375792635443 | P78: =TEXT(Table1[[#This Row],[Order_Date]],"mmm") -> Jan | Q78: =YEAR(Table1[[#This Row],[Order_Date]]) -> 2024 | R78: =Table1[[#This Row],[Profit]]/Table1[[#This Row],[Sales]] -> 0.14698376 | S78: =IF(I78<0,0,I78) -> 179780
A79: ORD082 | B79: 45312 | C79: CUST13 | D79: Monitor | E79: Electronics | F79: 4 | G79: 37588 | H79: 5 | I79: 142834.4 | J79: -4571.63 | K79: USA | L79: Credit Card | M79: 2024 | N79: 1 | O79: -0.032006505 | P79: =TEXT(Table1[[#This Row],[Order_Date]],"mmm") -> Jan | Q79: =YEAR(Table1[[#This Row],[Order_Date]]) -> 2024 | R79: =Table1[[#This Row],[Profit]]/Table1[[#This Row],[Sales]] -> -0.032006505 | S79: =IF(I79<0,0,I79) -> 142834.4
A80: ORD083 | B80: 45411 | C80: CUST18 | D80: Keyboard | E80: Accessories | F80: 2 | G80: 30618 | H80: 10 | I80: 55112.4 | J80: 9189.24 | K80: UK | L80: Debit Card | M80: 2024 | N80: 4 | O80: 0.16673634245650706 | P80: =TEXT(Table1[[#This Row],[Order_Date]],"mmm") -> Apr | Q80: =YEAR(Table1[[#This Row],[Order_Date]]) -> 2024 | R80: =Table1[[#This Row],[Profit]]/Table1[[#This Row],[Sales]] -> 0.16673634 | S80: =IF(I80<0,0,I80) -> 55112.4
A81: ORD084 | B81: 45369 | C81: CUST13 | D81: Mouse | E81: Accessories | F81: 4 | G81: 45740 | H81: 10 | I81: 164664 | J81: 13623.36 | K81: Canada | L81: Debit Card | M81: 2024 | N81: 3 | O81: 0.082734295 | P81: =TEXT(Table1[[#This Row],[Order_Date]],"mmm") -> Mar | Q81: =YEAR(Table1[[#This Row],[Order_Date]]) -> 2024 | R81: =Table1[[#This Row],[Profit]]/Table1[[#This Row],[Sales]] -> 0.082734295 | S81: =IF(I81<0,0,I81) -> 164664
A82: ORD085 | B82: 45460 | C82: CUST1 | D82: Monitor | E82: Electronics | F82: 2 | G82: 46327 | H82: 10 | I82: 83388.6 | J82: -7607.06 | K82: India | L82: Net Banking | M82: 2024 | N82: 6 | O82: -0.09122422 | P82: =TEXT(Table1[[#This Row],[Order_Date]],"mmm") -> Jun | Q82: =YEAR(Table1[[#This Row],[Order_Date]]) -> 2024 | R82: =Table1[[#This Row],[Profit]]/Table1[[#This Row],[Sales]] -> -0.09122422 | S82: =IF(I82<0,0,I82) -> 83388.6
A83: ORD086 | B83: 45340 | C83: CUST5 | D83: Headphones | E83: Accessories | F83: 1 | G83: 40284 | H83: 10 | I83: 36255.6 | J83: -449.5 | K83: India | L83: Debit Card | M83: 2024 | N83: 2 | O83: -0.012398085 | P83: =TEXT(Table1[[#This Row],[Order_Date]],"mmm") -> Feb | Q83: =YEAR(Table1[[#This Row],[Order_Date]]) -> 2024 | R83: =Table1[[#This Row],[Profit]]/Table1[[#This Row],[Sales]] -> -0.012398085 | S83: =IF(I83<0,0,I83) -> 36255.6
A84: ORD087 | B84: 45315 | C84: CUST11 | D84: Keyboard | E84: Accessories | F84: -2 | G84: 38482 | H84: 10 | I84: -69267.6 | J84: -13364.76 | K84: USA | L84: Debit Card | M84: 2024 | N84: 1 | O84: 0.19294388718535072 | P84: =TEXT(Table1[[#This Row],[Order_Date]],"mmm") -> Jan | Q84: =YEAR(Table1[[#This Row],[Order_Date]]) -> 2024 | R84: =Table1[[#This Row],[Profit]]/Table1[[#This Row],[Sales]] -> 0.19294389 | S84: =IF(I84<0,0,I84) -> 0
A85: ORD088 | B85: 45356 | C85: CUST10 | D85: Monitor | E85: Electronics | F85: 2 | G85: 11283 | H85: 10 | I85: 20309.4 | J85: 5394.57 | K85: India | L85: Net Banking | M85: 2024 | N85: 3 | O85: 0.26561937 | P85: =TEXT(Table1[[#This Row],[Order_Date]],"mmm") -> Mar | Q85: =YEAR(Table1[[#This Row],[Order_Date]]) -> 2024 | R85: =Table1[[#This Row],[Profit]]/Table1[[#This Row],[Sales]] -> 0.26561937 | S85: =IF(I85<0,0,I85) -> 20309.4
A86: ORD089 | B86: 45464 | C86: CUST18 | D86: Laptop | E86: Electronics | F86: 0 | G86: 49924 | H86: 5 | I86: 0 | J86: 0 | K86: India | L86: Debit Card | M86: 2024 | N86: 6 | P86: =TEXT(Table1[[#This Row],[Order_Date]],"mmm") -> Jun | Q86: =YEAR(Table1[[#This Row],[Order_Date]]) -> 2024 | R86: =Table1[[#This Row],[Profit]]/Table1[[#This Row],[Sales]] -> #DIV/0! | S86: =IF(I86<0,0,I86) -> 0
A87: ORD090 | B87: 45464 | C87: CUST13 | D87: Monitor | E87: Electronics | F87: -1 | G87: 30304 | H87: 10 | I87: -27273.6 | J87: -4612.82 | K87: India | L87: Credit Card | M87: 2024 | N87: 6 | O87: 0.16913132113105714 | P87: =TEXT(Table1[[#This Row],[Order_Date]],"mmm") -> Jun | Q87: =YEAR(Table1[[#This Row],[Order_Date]]) -> 2024 | R87: =Table1[[#This Row],[Profit]]/Table1[[#This Row],[Sales]] -> 0.16913132 | S87: =IF(I87<0,0,I87) -> 0
A88: ORD091 | B88: 45418 | C88: CUST3 | D88: Keyboard | E88: Accessories | F88: -2 | G88: 41102 | H88: 20 | I88: -65763.2 | J88: -2051.98 | K88: UK | L88: Net Banking | M88: 2024 | N88: 5 | O88: 0.031202557 | P88: =TEXT(Table1[[#This Row],[Order_Date]],"mmm") -> May | Q88: =YEAR(Table1[[#This Row],[Order_Date]]) -> 2024 | R88: =Table1[[#This Row],[Profit]]/Table1[[#This Row],[Sales]] -> 0.031202557 | S88: =IF(I88<0,0,I88) -> 0
A89: ORD092 | B89: 45448 | C89: CUST8 | D89: Laptop | E89: Electronics | F89: 0 | G89: 3471 | H89: 0 | I89: 0 | J89: 0 | K89: Canada | L89: Debit Card | M89: 2024 | N89: 6 | P89: =TEXT(Table1[[#This Row],[Order_Date]],"mmm") -> Jun | Q89: =YEAR(Table1[[#This Row],[Order_Date]]) -> 2024 | R89: =Table1[[#This Row],[Profit]]/Table1[[#This Row],[Sales]] -> #DIV/0! | S89: =IF(I89<0,0,I89) -> 0
A90: ORD093 | B90: 45459 | C90: CUST16 | D90: Mouse | E90: Accessories | F90: 4 | G90: 38991 | H90: 5 | I90: 148165.8 | J90: 37658.64 | K90: UK | L90: UPI | M90: 2024 | N90: 6 | O90: 0.2541655361763646 | P90: =TEXT(Table1[[#This Row],[Order_Date]],"mmm") -> Jun | Q90: =YEAR(Table1[[#This Row],[Order_Date]]) -> 2024 | R90: =Table1[[#This Row],[Profit]]/Table1[[#This Row],[Sales]] -> 0.25416554 | S90: =IF(I90<0,0,I90) -> 148165.8
A91: ORD094 | B91: 45294 | C91: CUST4 | D91: Mouse | E91: Accessories | F91: 3 | G91: 14738 | H91: 15 | I91: 37581.9 | J91: 2926.82 | K91: UK | L91: UPI | M91: 2024 | N91: 1 | O91: 0.077878447 | P91: =TEXT(Table1[[#This Row],[Order_Date]],"mmm") -> Jan | Q91: =YEAR(Table1[[#This Row],[Order_Date]]) -> 2024 | R91: =Table1[[#This Row],[Profit]]/Table1[[#This Row],[Sales]] -> 0.077878447 | S91: =IF(I91<0,0,I91) -> 37581.9
A92: ORD095 | B92: 45408 | C92: CUST7 | D92: Keyboard | E92: Accessories | F92: 2 | G92: 12939 | H92: 0 | I92: 25878 | J92: 7235.6 | K92: India | L92: UPI | M92: 2024 | N92: 4 | O92: 0.27960429708632817 | P92: =TEXT(Table1[[#This Row],[Order_Date]],"mmm") -> Apr | Q92: =YEAR(Table1[[#This Row],[Order_Date]]) -> 2024 | R92: =Table1[[#This Row],[Profit]]/Table1[[#This Row],[Sales]] -> 0.2796043 | S92: =IF(I92<0,0,I92) -> 25878

Sheet Analysis
A1: Total Revenue | B1: Total Orders | C1: Total Profit | D1: Average Order Value | E1: Month | F1: Sum of Net Sales Column | H1: Customer_ID | I1: Sum of Net Sales Column | L1: Country | M1: Sum of Net Sales Column | P1: Category | Q1: Count of Profit % Column
A2: =SUM(Cleaned_Data!J:J) -> 350288.71 | B2: =COUNTA(Cleaned_Data!A:A) -> 92 | C2: =SUM(Cleaned_Data!J:J) -> 350288.71 | D2: =A2/B2 -> 3807.486 | E2: Jan | F2: 1032762.4 | H2: CUST13 | I2: 858423 | L2: Canada | M2: 956588.65 | P2: Accessories | Q2: 50
E3: Feb | F3: 331925.4 | H3: CUST10 | I3: 589678.4 | L3: India | M3: 1021791.2 | P3: Electronics | Q3: 41
E4: Mar | F4: 389816.3 | H4: CUST16 | I4: 538009.9 | L4: UK | M4: 1338248.8 | P4: Grand Total | Q4: 91
E5: Apr | F5: 391150.3 | H5: CUST14 | I5: 419234.85 | L5: USA | M5: 812391.9
E6: May | F6: 447512.9 | H6: CUST18 | I6: 366994.1 | L6: Grand Total | M6: 4129020.5
E7: Jun | F7: 1234960.9 | H7: CUST6 | I7: 348493.05
E8: Aug | F8: 0 | H8: CUST8 | I8: 241900.9
E9: Oct | F9: 205348.5 | H9: CUST4 | I9: 209632.7
E10: Nov | F10: 80434.8 | H10: CUST1 | I10: 129399.3
E11: Dec | F11: 15109 | H11: CUST2 | I11: 116673
E12: Grand Total | F12: 4129020.5 | H12: Grand Total | I12: 3818439.2

Sheet Dashboard
K1: E-Commerce Sales Performance Dashboard
B4: Total Revenue | D4: Total Orders | F4: Total Profit | H4: Average Order Value
B5: =Analysis!A2 -> 350288.71 | D5: =Analysis!B2 -> 92 | F5: =Analysis!C2 -> 350288.71 | H5: =Analysis!D2 -> 3807.486
